README.rst
flask_elastic.py
setup.py
Flask_Elastic.egg-info/PKG-INFO
Flask_Elastic.egg-info/SOURCES.txt
Flask_Elastic.egg-info/dependency_links.txt
Flask_Elastic.egg-info/not-zip-safe
Flask_Elastic.egg-info/requires.txt
Flask_Elastic.egg-info/top_level.txt