Metadata-Version: 1.1
Name: Flask-Elastic
Version: 0.2
Summary: Integrates official client for Elasticsearch into Flask
Home-page: UNKNOWN
Author: Marcel Tschopp
Author-email: mt@corova.net
License: BSD
Download-URL: https://github.com/bbmogool/flask-elastic/
Platform: any
Classifier: Environment :: Web Environment
Classifier: Intended Audience :: Developers
Classifier: License :: OSI Approved :: BSD License
Classifier: Operating System :: OS Independent
Classifier: Programming Language :: Python
Classifier: Topic :: Internet :: WWW/HTTP :: Dynamic Content
Classifier: Topic :: Software Development :: Libraries :: Python Modules
